phothumb/__init__.py
phothumb-1.4.1.dist-info/DESCRIPTION.rst
phothumb-1.4.1.dist-info/METADATA
phothumb-1.4.1.dist-info/RECORD
phothumb-1.4.1.dist-info/WHEEL
phothumb-1.4.1.dist-info/metadata.json
phothumb-1.4.1.dist-info/top_level.txt
