Metadata-Version: 2.0
Name: phothumb
Version: 1.4.1
Summary: Photo thumbnail library based on Pillow
Home-page: https://github.com/nitipit/phothumb
Author: Nitipit Nontasuwan
Author-email: nitipit@gmail.com
License: MIT
Keywords: photo image thumbnail
Platform: UNKNOWN
Classifier: Programming Language :: Python :: 3
Requires-Dist: pillow
